litebird_sim/__init__.py
litebird_sim/bandpasses.py
litebird_sim/beam_convolution.py
litebird_sim/beam_synthesis.py
litebird_sim/compress.py
litebird_sim/constants.py
litebird_sim/coordinates.py
litebird_sim/datautils/Cls_Planck2018_for_PTEP_2020_r0.fits
litebird_sim/datautils/Cls_Planck2018_for_PTEP_2020_tensor_r1.fits
litebird_sim/default_imo/schema.json.gz
litebird_sim/detectors.py
litebird_sim/dipole.py
litebird_sim/distribute.py
litebird_sim/gaindrifts.py
litebird_sim/grasp2alm.py
litebird_sim/healpix.py
litebird_sim/hwp.py
litebird_sim/hwp_diff_emiss.py
litebird_sim/hwp_sys/__init__.py
litebird_sim/hwp_sys/bandpass_template_module.py
litebird_sim/hwp_sys/hwp_sys.py
litebird_sim/imo/__init__.py
litebird_sim/imo/imo.py
litebird_sim/imobrowser.py
litebird_sim/install_imo.py
litebird_sim/io.py
litebird_sim/madam.py
litebird_sim/mapmaking/__init__.py
litebird_sim/mapmaking/binner.py
litebird_sim/mapmaking/brahmap_gls.py
litebird_sim/mapmaking/common.py
litebird_sim/mapmaking/destriper.py
litebird_sim/mbs/__init__.py
litebird_sim/mbs/fg_models/pysm_ame_1.cfg
litebird_sim/mbs/fg_models/pysm_ame_2.cfg
litebird_sim/mbs/fg_models/pysm_co_1.cfg
litebird_sim/mbs/fg_models/pysm_co_2.cfg
litebird_sim/mbs/fg_models/pysm_co_3.cfg
litebird_sim/mbs/fg_models/pysm_dust_0.cfg
litebird_sim/mbs/fg_models/pysm_dust_1.cfg
litebird_sim/mbs/fg_models/pysm_dust_10.cfg
litebird_sim/mbs/fg_models/pysm_dust_11.cfg
litebird_sim/mbs/fg_models/pysm_dust_12.cfg
litebird_sim/mbs/fg_models/pysm_dust_2.cfg
litebird_sim/mbs/fg_models/pysm_dust_3.cfg
litebird_sim/mbs/fg_models/pysm_dust_4.cfg
litebird_sim/mbs/fg_models/pysm_dust_5.cfg
litebird_sim/mbs/fg_models/pysm_dust_6.cfg
litebird_sim/mbs/fg_models/pysm_dust_7.cfg
litebird_sim/mbs/fg_models/pysm_dust_8.cfg
litebird_sim/mbs/fg_models/pysm_dust_9.cfg
litebird_sim/mbs/fg_models/pysm_freefree_1.cfg
litebird_sim/mbs/fg_models/pysm_synch_0.cfg
litebird_sim/mbs/fg_models/pysm_synch_1.cfg
litebird_sim/mbs/fg_models/pysm_synch_2.cfg
litebird_sim-0.16.0.dist-info/LICENSE
litebird_sim-0.16.0.dist-info/METADATA
litebird_sim-0.16.0.dist-info/WHEEL
litebird_sim-0.16.0.dist-info/RECORD
