Metadata-Version: 2.3
Name: litebird_sim
Version: 0.16.0
Summary: Simulation tools for the LiteBIRD experiment
License: GPL3
Author: Tomasi Maurizio
Author-email: maurizio.tomasi@unimi.it
Requires-Python: >=3.10,<3.14
Classifier: License :: Other/Proprietary License
Classifier: Programming Language :: Python :: 3
Classifier: Programming Language :: Python :: 3.10
Classifier: Programming Language :: Python :: 3.11
Classifier: Programming Language :: Python :: 3.12
Classifier: Programming Language :: Python :: 3.13
Requires-Dist: PyGithub (>=2.6.1,<3.0.0)
Requires-Dist: asciimatics (>=1.15.0,<2.0.0)
Requires-Dist: astropy (==6.1.7)
Requires-Dist: deprecation (>=2.1.0,<3.0.0)
Requires-Dist: ducc0 (>=0.38.0,<0.39.0)
Requires-Dist: h5py (>=3.9,<4.0)
Requires-Dist: healpy (>=1.18.1,<2.0.0)
Requires-Dist: jinja2 (>=3.1,<4.0)
Requires-Dist: jplephem (>=2.22,<3.0)
Requires-Dist: libinsdb (>=0.9.0,<0.10.0)
Requires-Dist: markdown (>=3.8,<4.0)
Requires-Dist: markdown-katex (>=202406.1035,<202407.0)
Requires-Dist: matplotlib (>=3.10.3,<4.0.0)
Requires-Dist: numba (>=0.61.2,<0.62.0)
Requires-Dist: numpy (>=1.26.4,<2.0.0)
Requires-Dist: poetry-plugin-export (>=1.9.0,<2.0.0)
Requires-Dist: pre-commit (>=4.2.0,<5.0.0)
Requires-Dist: pydata-sphinx-theme (>=0.16.1,<0.17.0)
Requires-Dist: pyperclip (>=1.9.0,<2.0.0)
Requires-Dist: pysm3 (>=3.4.2,<4.0.0)
Requires-Dist: pytest (>=8.3.5,<9.0.0)
Requires-Dist: pyyaml (>=6.0,<7.0)
Requires-Dist: requests (>=2.32.0,<3.0.0)
Requires-Dist: rich (>=14.0.0,<15.0.0)
Requires-Dist: ruff (>=0.11.11,<0.12.0)
Requires-Dist: scipy (>=1.14.0,<2.0.0)
Requires-Dist: sphinx (>=8.1.3,<9.0.0)
Requires-Dist: sphinxcontrib-bibtex (>=2.6.3,<3.0.0)
Requires-Dist: sphinxcontrib-contentui (>=0.2.5,<0.3.0)
Requires-Dist: sphinxcontrib.asciinema (>=0.3.7,<0.4.0)
Requires-Dist: tomlkit (>=0.12.1,<0.13.0)
